{
    "gridHeight": 5,
    "entityInitialSpawns": [],
    "entitySpawnOverrides": [],
    "maxLayers": 5,
    "bore": false,
    "wallStyle": {
        "multiplier": 1,
        "style": "STATIC",
        "zoom": 1,
        "exponent": 1
    },
    "tiles": [
        {
            "ceiling": "NEVER",
            "entityInitialSpawns": [],
            "entitySpawnOverrides": [],
            "placeMode": "CENTER_HEIGHT",
            "south": "NEVER",
            "north": "NEVER",
            "objects": ["structure/prismarine_temple/cross-floor-1"],
            "smartBore": false,
            "east": "NEVER",
            "rareObjects": [],
            "west": "NEVER",
            "loot": {
                "mode": "ADD",
                "tables": [],
                "multiplier": 1
            },
            "floor": "REQUIRED"
        },
        {
            "ceiling": "NEVER",
            "entityInitialSpawns": [],
            "entitySpawnOverrides": [],
            "placeMode": "CENTER_HEIGHT",
            "south": "NEVER",
            "north": "REQUIRED",
            "objects": [
                "structure/prismarine_temple/t-connect-floor-1",
                "structure/prismarine_temple/t-connect-floor-2"
            ],
            "smartBore": false,
            "east": "NEVER",
            "rareObjects": [],
            "west": "NEVER",
            "loot": {
                "mode": "ADD",
                "tables": [],
                "multiplier": 1
            },
            "floor": "REQUIRED"
        },
        {
            "ceiling": "NEVER",
            "entityInitialSpawns": [],
            "entitySpawnOverrides": [],
            "placeMode": "CENTER_HEIGHT",
            "south": "REQUIRED",
            "north": "REQUIRED",
            "objects": [
                "structure/prismarine_temple/hall-floor-1",
                "structure/prismarine_temple/hall-floor-2"
            ],
            "smartBore": false,
            "east": "NEVER",
            "rareObjects": [],
            "west": "NEVER",
            "loot": {
                "mode": "ADD",
                "tables": [],
                "multiplier": 1
            },
            "floor": "REQUIRED"
        },
        {
            "ceiling": "NEVER",
            "entityInitialSpawns": [],
            "entitySpawnOverrides": [],
            "placeMode": "CENTER_HEIGHT",
            "south": "NEVER",
            "north": "REQUIRED",
            "objects": ["structure/prismarine_temple/corner-floor-1"],
            "smartBore": false,
            "east": "REQUIRED",
            "rareObjects": [],
            "west": "NEVER",
            "loot": {
                "mode": "ADD",
                "tables": [],
                "multiplier": 1
            },
            "floor": "REQUIRED"
        },
        {
            "ceiling": "REQUIRED",
            "entityInitialSpawns": [],
            "entitySpawnOverrides": [],
            "placeMode": "CENTER_HEIGHT",
            "south": "NEVER",
            "north": "REQUIRED",
            "objects": ["structure/prismarine_temple/room-floor-1"],
            "smartBore": false,
            "east": "REQUIRED",
            "rareObjects": [],
            "west": "REQUIRED",
            "loot": {
                "mode": "ADD",
                "tables": [],
                "multiplier": 1
            },
            "floor": "NEVER"
        },
        {
            "ceiling": "REQUIRED",
            "entityInitialSpawns": [],
            "entitySpawnOverrides": [],
            "placeMode": "CENTER_HEIGHT",
            "south": "REQUIRED",
            "north": "REQUIRED",
            "objects": ["structure/prismarine_temple/walled-room-floor-1"],
            "smartBore": false,
            "east": "REQUIRED",
            "rareObjects": [],
            "west": "REQUIRED",
            "loot": {
                "mode": "ADD",
                "tables": [],
                "multiplier": 1
            },
            "floor": "NEVER"
        },
        {
            "ceiling": "REQUIRED",
            "entityInitialSpawns": [],
            "entitySpawnOverrides": [],
            "placeMode": "CENTER_HEIGHT",
            "south": "NEVER",
            "north": "NEVER",
            "objects": ["structure/prismarine_temple/cross-ceiling-1"],
            "smartBore": false,
            "east": "NEVER",
            "rareObjects": [],
            "west": "NEVER",
            "loot": {
                "mode": "ADD",
                "tables": [],
                "multiplier": 1
            },
            "floor": "NEVER"
        },
        {
            "ceiling": "REQUIRED",
            "entityInitialSpawns": [],
            "entitySpawnOverrides": [],
            "placeMode": "CENTER_HEIGHT",
            "south": "NEVER",
            "north": "REQUIRED",
            "objects": ["structure/prismarine_temple/t-connect-ceiling-1"],
            "smartBore": false,
            "east": "NEVER",
            "rareObjects": [],
            "west": "NEVER",
            "loot": {
                "mode": "ADD",
                "tables": [],
                "multiplier": 1
            },
            "floor": "NEVER"
        },
        {
            "ceiling": "REQUIRED",
            "entityInitialSpawns": [],
            "entitySpawnOverrides": [],
            "placeMode": "CENTER_HEIGHT",
            "south": "REQUIRED",
            "north": "REQUIRED",
            "objects": ["structure/prismarine_temple/hall-ceiling-1"],
            "smartBore": false,
            "east": "NEVER",
            "rareObjects": [],
            "west": "NEVER",
            "loot": {
                "mode": "ADD",
                "tables": [],
                "multiplier": 1
            },
            "floor": "NEVER"
        },
        {
            "ceiling": "REQUIRED",
            "entityInitialSpawns": [],
            "entitySpawnOverrides": [],
            "placeMode": "CENTER_HEIGHT",
            "south": "NEVER",
            "north": "REQUIRED",
            "objects": ["structure/prismarine_temple/corner-ceiling-1"],
            "smartBore": false,
            "east": "REQUIRED",
            "rareObjects": [],
            "west": "NEVER",
            "loot": {
                "mode": "ADD",
                "tables": [],
                "multiplier": 1
            },
            "floor": "NEVER"
        },
        {
            "ceiling": "REQUIRED",
            "entityInitialSpawns": [],
            "entitySpawnOverrides": [],
            "placeMode": "CENTER_HEIGHT",
            "south": "NEVER",
            "north": "REQUIRED",
            "objects": ["structure/prismarine_temple/room-ceiling-1"],
            "smartBore": false,
            "east": "REQUIRED",
            "rareObjects": [],
            "west": "REQUIRED",
            "loot": {
                "mode": "ADD",
                "tables": [],
                "multiplier": 1
            },
            "floor": "NEVER"
        },
        {
            "ceiling": "REQUIRED",
            "entityInitialSpawns": [],
            "entitySpawnOverrides": [],
            "placeMode": "CENTER_HEIGHT",
            "south": "REQUIRED",
            "north": "REQUIRED",
            "objects": ["structure/prismarine_temple/walled-room-ceiling-1"],
            "smartBore": false,
            "east": "REQUIRED",
            "rareObjects": [],
            "west": "REQUIRED",
            "loot": {
                "mode": "ADD",
                "tables": [],
                "multiplier": 1
            },
            "floor": "NEVER"
        },
        {
            "ceiling": "NEVER",
            "entityInitialSpawns": [],
            "entitySpawnOverrides": [],
            "placeMode": "CENTER_HEIGHT",
            "south": "NEVER",
            "north": "NEVER",
            "objects": ["structure/prismarine_temple/cross-opening-1"],
            "smartBore": false,
            "east": "NEVER",
            "rareObjects": [],
            "west": "NEVER",
            "loot": {
                "mode": "ADD",
                "tables": [],
                "multiplier": 1
            },
            "floor": "NEVER"
        },
        {
            "ceiling": "NEVER",
            "entityInitialSpawns": [],
            "entitySpawnOverrides": [],
            "placeMode": "CENTER_HEIGHT",
            "south": "NEVER",
            "north": "REQUIRED",
            "objects": ["structure/prismarine_temple/t-connect-opening-1"],
            "smartBore": false,
            "east": "NEVER",
            "rareObjects": [],
            "west": "NEVER",
            "loot": {
                "mode": "ADD",
                "tables": [],
                "multiplier": 1
            },
            "floor": "NEVER"
        },
        {
            "ceiling": "NEVER",
            "entityInitialSpawns": [],
            "entitySpawnOverrides": [],
            "placeMode": "CENTER_HEIGHT",
            "south": "REQUIRED",
            "north": "REQUIRED",
            "objects": ["structure/prismarine_temple/hall-opening-1"],
            "smartBore": false,
            "east": "NEVER",
            "rareObjects": [],
            "west": "NEVER",
            "loot": {
                "mode": "ADD",
                "tables": [],
                "multiplier": 1
            },
            "floor": "NEVER"
        },
        {
            "ceiling": "NEVER",
            "entityInitialSpawns": [],
            "entitySpawnOverrides": [],
            "placeMode": "CENTER_HEIGHT",
            "south": "NEVER",
            "north": "REQUIRED",
            "objects": [
                "structure/prismarine_temple/corner-opening-1",
                "structure/prismarine_temple/corner-opening-2"
            ],
            "smartBore": false,
            "east": "REQUIRED",
            "rareObjects": [],
            "west": "NEVER",
            "loot": {
                "mode": "ADD",
                "tables": [],
                "multiplier": 1
            },
            "floor": "NEVER"
        },
        {
            "ceiling": "NEVER",
            "entityInitialSpawns": [],
            "entitySpawnOverrides": [],
            "placeMode": "CENTER_HEIGHT",
            "south": "NEVER",
            "north": "REQUIRED",
            "objects": [
                "structure/prismarine_temple/room-opening-1",
                "structure/prismarine_temple/room-opening-2"
            ],
            "smartBore": false,
            "east": "REQUIRED",
            "rareObjects": [],
            "west": "REQUIRED",
            "loot": {
                "mode": "ADD",
                "tables": [],
                "multiplier": 1
            },
            "floor": "NEVER"
        },
        {
            "ceiling": "NEVER",
            "entityInitialSpawns": [],
            "entitySpawnOverrides": [],
            "placeMode": "CENTER_HEIGHT",
            "south": "REQUIRED",
            "north": "REQUIRED",
            "objects": [
                "structure/prismarine_temple/walled-room-opening-1",
                "structure/prismarine_temple/walled-room-opening-2",
                "structure/prismarine_temple/walled-room-opening-3"
            ],
            "smartBore": false,
            "east": "REQUIRED",
            "rareObjects": [],
            "west": "REQUIRED",
            "loot": {
                "mode": "ADD",
                "tables": [],
                "multiplier": 1
            },
            "floor": "NEVER"
        },
        {
            "ceiling": "REQUIRED",
            "entityInitialSpawns": [],
            "entitySpawnOverrides": [],
            "placeMode": "CENTER_HEIGHT",
            "south": "NEVER",
            "north": "NEVER",
            "objects": ["structure/prismarine_temple/cross-encased-1"],
            "smartBore": false,
            "east": "NEVER",
            "rareObjects": [],
            "west": "NEVER",
            "loot": {
                "mode": "ADD",
                "tables": [],
                "multiplier": 1
            },
            "floor": "REQUIRED"
        },
        {
            "ceiling": "REQUIRED",
            "entityInitialSpawns": [],
            "entitySpawnOverrides": [],
            "placeMode": "CENTER_HEIGHT",
            "south": "NEVER",
            "north": "REQUIRED",
            "objects": [
                "structure/prismarine_temple/t-connect-encased-1",
                "structure/prismarine_temple/t-connect-encased-2",
                "structure/prismarine_temple/t-connect-encased-3"
            ],
            "smartBore": false,
            "east": "NEVER",
            "rareObjects": [],
            "west": "NEVER",
            "loot": {
                "mode": "ADD",
                "tables": [],
                "multiplier": 1
            },
            "floor": "REQUIRED"
        },
        {
            "ceiling": "REQUIRED",
            "entityInitialSpawns": [],
            "entitySpawnOverrides": [],
            "placeMode": "CENTER_HEIGHT",
            "south": "REQUIRED",
            "north": "REQUIRED",
            "objects": ["structure/prismarine_temple/hall-encased-1"],
            "smartBore": false,
            "east": "NEVER",
            "rareObjects": [],
            "west": "NEVER",
            "loot": {
                "mode": "ADD",
                "tables": [],
                "multiplier": 1
            },
            "floor": "REQUIRED"
        },
        {
            "ceiling": "REQUIRED",
            "entityInitialSpawns": [],
            "entitySpawnOverrides": [],
            "placeMode": "CENTER_HEIGHT",
            "south": "NEVER",
            "north": "REQUIRED",
            "objects": [
                "structure/prismarine_temple/corner-encased-1",
                "structure/prismarine_temple/corner-encased-2",
                "structure/prismarine_temple/corner-encased-3"
            ],
            "smartBore": false,
            "east": "REQUIRED",
            "rareObjects": [],
            "west": "NEVER",
            "loot": {
                "mode": "ADD",
                "tables": [],
                "multiplier": 1
            },
            "floor": "REQUIRED"
        },
        {
            "ceiling": "REQUIRED",
            "entityInitialSpawns": [],
            "entitySpawnOverrides": [],
            "placeMode": "CENTER_HEIGHT",
            "south": "NEVER",
            "north": "REQUIRED",
            "objects": ["structure/prismarine_temple/room-encased-1"],
            "smartBore": false,
            "east": "REQUIRED",
            "rareObjects": [],
            "west": "REQUIRED",
            "loot": {
                "mode": "ADD",
                "tables": [],
                "multiplier": 1
            },
            "floor": "REQUIRED"
        },
        {
            "ceiling": "REQUIRED",
            "entityInitialSpawns": [],
            "entitySpawnOverrides": [],
            "placeMode": "CENTER_HEIGHT",
            "south": "REQUIRED",
            "north": "REQUIRED",
            "objects": ["structure/prismarine_temple/walled-room-encased-1"],
            "smartBore": false,
            "east": "REQUIRED",
            "rareObjects": [],
            "west": "REQUIRED",
            "loot": {
                "mode": "ADD",
                "tables": [],
                "multiplier": 1
            },
            "floor": "REQUIRED"
        }
    ],
    "gridSize": 5,
    "wallChance": 0.26,
    "name": "prismarine_temple",
    "underwater": false,
    "loot": {
        "mode": "ADD",
        "tables": [],
        "multiplier": 2.5
    },
    "clamp": {
        "minimumHeight": 0,
        "maximumHeight": 255
    },
    "mergeEdges": false
}
