{
    "name": "Overworld",
    "version": 2,
    "environment": "NORMAL",
    "regions": [
        "hot",
        "tropical",
        "mushroom",
        "swamp",
        "temperate",
        "temperate",
        "tundra",
        "frozen",
        "mosaic"
    ],
    "loot": {
        "tables": [
            "global-treasure",
            "global-tools",
            "global-clutter"
        ]
    },
    "lootTries": 16,
    "decorate": true,
    "placeObjects": true,
    "debugSmartBore": false,
    "postProcessing": true,
    "carving": true,
    "caves": true,
    "caveLayers": [
        {
            "caveZoom": 1.25,
            "caveThickness": 2,
            "canBreakSurface": false,
            "verticalSlope": {
                "generator": {
                    "style": "IRIS",
                    "fracture": {
                        "style": "IRIS_THICK",
                        "zoom": 0.3,
                        "multiplier": 9
                    }
                },
                "max": 52,
                "min": 95
            },
            "horizontalSlope": {
                "generator": {
                    "style": "IRIS_THICK",
                    "fracture": {
                        "style": "IRIS_THICK",
                        "zoom": 0.3,
                        "multiplier": 9
                    }
                },
                "max": -110,
                "min": 110
            }
        },
        {
            "caveZoom": 0.89,
            "caveThickness": 1,
            "canBreakSurface": false,
            "verticalSlope": {
                "generator": {
                    "style": "IRIS_DOUBLE",
                    "zoom": 1.82,
                    "fracture": {
                        "style": "IRIS_THICK",
                        "zoom": 0.3,
                        "multiplier": 9
                    }
                },
                "max": 22,
                "min": 54
            },
            "horizontalSlope": {
                "generator": {
                    "style": "IRIS_THICK",
                    "zoom": 0.885,
                    "fracture": {
                        "style": "IRIS_THICK",
                        "zoom": 0.3,
                        "multiplier": 9
                    }
                },
                "max": -10,
                "min": 10
            }
        },
        {
            "caveZoom": 0.89,
            "caveThickness": 0.9,
            "canBreakSurface": true,
            "verticalSlope": {
                "generator": {
                    "style": "IRIS_DOUBLE",
                    "zoom": 1.12,
                    "fracture": {
                        "style": "IRIS_THICK",
                        "zoom": 0.3,
                        "multiplier": 9
                    }
                },
                "max": 103,
                "min": 175
            },
            "horizontalSlope": {
                "generator": {
                    "style": "IRIS_DOUBLE",
                    "zoom": 1.12,
                    "fracture": {
                        "style": "IRIS_THICK",
                        "zoom": 0.3,
                        "multiplier": 9
                    }
                },
                "max": -10,
                "min": 10
            }
        },
        {
            "caveZoom": 0.99,
            "caveThickness": 1.125,
            "canBreakSurface": false,
            "verticalSlope": {
                "generator": {
                    "style": "IRIS_DOUBLE",
                    "zoom": 1.12,
                    "fracture": {
                        "style": "IRIS_THICK",
                        "zoom": 0.3,
                        "multiplier": 9
                    }
                },
                "max": 91,
                "min": 155
            },
            "horizontalSlope": {
                "generator": {
                    "style": "IRIS_DOUBLE",
                    "zoom": 1.12,
                    "fracture": {
                        "style": "IRIS_THICK",
                        "zoom": 0.3,
                        "multiplier": 9
                    }
                },
                "max": -10,
                "min": 10
            }
        }
    ],
    "postProcessors": [
        {
            "phase": 0,
            "processor": "wall-painter"
        },
        {
            "phase": 0,
            "processor": "floating-block-remover"
        },
        {
            "phase": 0,
            "processor": "pothole-filler"
        },
        {
            "phase": 0,
            "processor": "nib-smoother"
        },
        {
            "phase": 1,
            "processor": "slabber"
        },
        {
            "phase": 2,
            "processor": "waterlogger"
        }
    ],
    "landChance": 0.72,
    "carveLayers": [
        {
            "minHeight": 115,
            "maxHeight": 236,
            "threshold": 0.335,
            "style": {
                "zoom": 7,
                "style": "FRACTAL_WATER"
            }
        },
        {
            "maxHeight": 82,
            "minHeight": -3,
            "threshold": 0.77,
            "style": {
                "zoom": 4,
                "style": "IRIS_DOUBLE"
            }
        }
    ],
    "vanillaStructures": true,
    "fluidHeight": 99,
    "biomeZoom": 2.25,
    "regionZoom": 7.5,
    "landBiomeStyle": {
        "style": "CELLULAR_IRIS_DOUBLE",
        "fracture": {
            "style": "FRACTAL_WATER",
            "multiplier": 25,
            "zoom": 0.455
        }
    },
    "seaBiomeStyle": {
        "style": "CELLULAR_IRIS_DOUBLE"
    },
    "shoreBiomeStyle": {
        "style": "CELLULAR_IRIS_DOUBLE"
    },
    "caveBiomeStyle": {
        "style": "CELLULAR_IRIS_DOUBLE"
    },
    "islandBiomeStyle": {
        "style": "CELLULAR_IRIS_DOUBLE"
    },
    "skylandBiomeStyle": {
        "style": "CELLULAR_IRIS_DOUBLE"
    },
    "regionStyle": {
        "style": "CELLULAR_IRIS_DOUBLE",
        "fracture": {
            "style": "FRACTAL_WATER",
            "multiplier": 75,
            "zoom": 0.4
        }
    },
    "continentalStyle": {
        "style": "CELLULAR_IRIS_DOUBLE",
        "zoom": 2.425
    },
    "continentZoom": 1,
    "dimensionAngleDeg": 19,
    "terrainZoom": 1,
    "landZoom": 1.25,
    "seaZoom": 2.25,
    "preventLeafDecay": true,
    "coordFractureZoom": 0.15,
    "coordFractureDistance": 126,
    "deposits": [
        {
            "minHeight": 19,
            "maxHeight": 150,
            "minSize": 22,
            "maxSize": 32,
            "minPerChunk": 4,
            "maxPerChunk": 12,
            "varience": 4,
            "palette": [
                "DIRT",
                "COARSE_DIRT"
            ]
        },
        {
            "minHeight": 45,
            "maxHeight": 140,
            "minSize": 19,
            "maxSize": 24,
            "minPerChunk": 4,
            "maxPerChunk": 12,
            "varience": 4,
            "palette": [
                "GRAVEL"
            ]
        },
        {
            "minHeight": 25,
            "maxHeight": 95,
            "minSize": 19,
            "maxSize": 24,
            "minPerChunk": 4,
            "maxPerChunk": 12,
            "varience": 4,
            "palette": [
                "ANDESITE"
            ]
        },
        {
            "minHeight": 35,
            "maxHeight": 100,
            "minSize": 19,
            "maxSize": 24,
            "minPerChunk": 4,
            "maxPerChunk": 12,
            "varience": 4,
            "palette": [
                "GRANITE"
            ]
        },
        {
            "minHeight": 45,
            "maxHeight": 115,
            "minSize": 19,
            "maxSize": 24,
            "minPerChunk": 4,
            "maxPerChunk": 12,
            "varience": 4,
            "palette": [
                "DIORITE"
            ]
        },
        {
            "minHeight": 2,
            "maxHeight": 18,
            "minSize": 2,
            "maxSize": 6,
            "minPerChunk": 1,
            "maxPerChunk": 2,
            "varience": 4,
            "palette": [
                "DIAMOND_ORE"
            ]
        },
        {
            "minHeight": 4,
            "maxHeight": 40,
            "minSize": 5,
            "maxSize": 9,
            "minPerChunk": 1,
            "maxPerChunk": 5,
            "varience": 7,
            "palette": [
                "minecraft:redstone_ore[lit=false]"
            ]
        },
        {
            "minHeight": 3,
            "maxHeight": 67,
            "minSize": 1,
            "maxSize": 2,
            "minPerChunk": 1,
            "maxPerChunk": 2,
            "varience": 3,
            "palette": [
                "GOLD_ORE"
            ]
        },
        {
            "minHeight": 3,
            "maxHeight": 45,
            "minSize": 3,
            "maxSize": 8,
            "minPerChunk": 0,
            "maxPerChunk": 1,
            "varience": 5,
            "palette": [
                "LAPIS_ORE"
            ]
        },
        {
            "minHeight": 1,
            "maxHeight": 122,
            "minSize": 6,
            "maxSize": 9,
            "minPerChunk": 4,
            "maxPerChunk": 9,
            "varience": 7,
            "palette": [
                "IRON_ORE"
            ]
        },
        {
            "minHeight": 1,
            "maxHeight": 175,
            "minSize": 9,
            "maxSize": 12,
            "minPerChunk": 5,
            "maxPerChunk": 10,
            "varience": 9,
            "palette": [
                "COAL_ORE"
            ]
        }
    ],
    "mutations": [
        {
            "sideA": [
                "swamp-roofed",
                "swamp-dark-oak-denmyre"
            ],
            "sideB": [
                "mushroom-forest",
                "mushroom-crimson-forest",
                "mushroom-warped-forest"
            ],
            "radius": 12,
            "checks": 8,
            "objects": [
                {
                    "chance": 0.4,
                    "density": 1,
                    "rotation": {
                        "yAxis": {
                            "min": 0,
                            "max": 0,
                            "interval": 90,
                            "enabled": true
                        },
                        "enabled": true
                    },
                    "place": [
                        "dual-tree/corrupted-swamp-1",
                        "dual-tree/corrupted-swamp-2",
                        "dual-tree/corrupted-swamp-3",
                        "dual-tree/corrupted-swamp-4",
                        "dual-tree/corrupted-swamp-5",
                        "dual-tree/corrupted-swamp-6",
                        "dual-tree/corrupted-swamp-7",
                        "dual-tree/corrupted-swamp-8",
                        "dual-tree/corrupted-swamp-9",
                        "dual-tree/corrupted-swamp-10"
                    ]
                }
            ]
        },
        {
            "sideA": [
                "tropical-beach"
            ],
            "sideB": [
                "tropical-rainforest"
            ],
            "radius": 12,
            "checks": 8,
            "objects": [
                {
                    "chance": 0.01,
                    "density": 1,
                    "translate": {
                        "x": 0,
                        "y": -3,
                        "z": 0
                    },
                    "rotation": {
                        "yAxis": {
                            "min": 0,
                            "max": 0,
                            "interval": 90,
                            "enabled": true
                        },
                        "enabled": true
                    },
                    "place": [
                        "beach-islander/easterHead1"
                    ]
                }
            ]
        },
        {
            "sideA": [
                "tropical-beach",
                "hot-beach"
            ],
            "sideB": [
                "mushroom-forest",
                "mushroom-crimson-forest",
                "mushroom-warped-forest"
            ],
            "radius": 12,
            "checks": 8,
            "objects": [
                {
                    "chance": 0.4,
                    "density": 1,
                    "rotation": {
                        "yAxis": {
                            "min": 0,
                            "max": 0,
                            "interval": 90,
                            "enabled": true
                        },
                        "enabled": true
                    },
                    "place": [
                        "dual-tree/infested-palm-1",
                        "dual-tree/infested-palm-2",
                        "dual-tree/infested-palm-3",
                        "dual-tree/infested-palm-4",
                        "dual-tree/infested-palm-5"
                    ]
                }
            ]
        },
        {
            "sideA": [
                "tropical-beach"
            ],
            "sideB": [
                "tropical-rainforest",
                "tropical-bamboo-forest"
            ],
            "radius": 12,
            "checks": 8,
            "objects": [
                {
                    "chance": 0.4,
                    "density": 1,
                    "edit": [
                        {
                            "find": [
                                "SAND"
                            ],
                            "replace": [
                                "SPRUCE_LEAVES"
                            ]
                        }
                    ],
                    "rotation": {
                        "yAxis": {
                            "min": 0,
                            "max": 0,
                            "interval": 90,
                            "enabled": true
                        },
                        "enabled": true
                    },
                    "place": [
                        "dual-tree/sandy-jungle-1",
                        "dual-tree/sandy-jungle-2",
                        "dual-tree/sandy-jungle-3",
                        "dual-tree/sandy-jungle-4"
                    ],
                    "translate": {
                        "x": 0,
                        "y": -2,
                        "z": 0
                    }
                }
            ]
        }
    ]
}