{
    "name": "Frozen Cavern",
    "layers": [
        {
            "dispersion": "IRIS",
            "terrainZoom": 0.2,
            "minHeight": 1,
            "maxHeight": 2,
            "palette": [
                "BLUE_ICE",
                "PACKED_ICE",
                "ICE",
                "ICE",
                "ICE",
                "ICE",
                "ICE",
                "ICE"
            ]
        },
        {
            "dispersion": "IRIS",
            "terrainZoom": 0.2,
            "minHeight": 1,
            "maxHeight": 1,
            "palette": [
                "ICE"
            ]
        },
        {
            "minHeight": 2,
            "maxHeight": 3,
            "dispersion": "IRIS",
            "terrainZoom": 0.825,
            "palette": [
                "SAND",
                "CLAY",
                "SAND",
                "GRAVEL",
                "SAND",
                "DIRT",
                "SAND",
                "SAND"
            ]
        }
    ],
    "slab": {
        "dispersion": "IRIS",
        "terrainZoom": 0.5,
        "palette": [
            "minecraft:cobblestone_slab[type=bottom,waterlogged=false]",
            "minecraft:mossy_cobblestone_slab[type=bottom,waterlogged=false]",
            "AIR"
        ]
    },
    "decorators": [
        {
            "zoom": 0.3,
            "chance": 0.02,
            "palette": [
                "COBWEB"
            ],
            "dispersion": "STATIC",
            "variance": "STATIC"
        },
        {
            "zoom": 0.3,
            "chance": 0.01,
            "palette": [
                "CORNFLOWER"
            ],
            "dispersion": "STATIC",
            "variance": "STATIC"
        },
        {
            "zoom": 0.3,
            "chance": 0.001,
            "palette": [
                "PRISMARINE_WALL"
            ],
            "dispersion": "STATIC",
            "variance": "STATIC"
        }
    ],
    "generators":[
        {
            "generator": "plain",
            "min": 4,
            "max": 6
        },
        {
            "generator": "wavy",
            "min": 2,
            "max": 5
        }
    ],
    "derivative": "FROZEN_OCEAN"
}