{
    "name": "Murky Cavern",
    "layers": [
        {
            "maxHeight": 2,
            "dispersion": {"style": "STATIC"},
            "terrainZoom": 0.1,
            "minHeight": 1,
            "palette": [
                "STONE",
                "COBBLESTONE",
                "COBBLESTONE",
                "MOSSY_COBBLESTONE",
                "GRASS_BLOCK",
                "GRASS_BLOCK"
            ]
        }
    ],
    "slab": {
        "style": {"style": "STATIC"},
        "palette": [
            "minecraft:cobblestone_slab[type=bottom,waterlogged=false]",
            "minecraft:mossy_cobblestone_slab[type=bottom,waterlogged=false]",
            "AIR"
        ]
    },
    "decorators": [
        {
            "zoom": 0.3,
            "chance": 0.05,
            "palette": [
                "BROWN_MUSHROOM",
                "RED_MUSHROOM"
            ],
            "dispersion": {"style": "STATIC"},
            "variance": {"style": "STATIC"}
                    },
        {
            "zoom": 0.3,
            "chance": 0.001,
            "palette": [
                "COBWEB"
            ],
            "dispersion": {"style": "STATIC"},
            "variance": {"style": "STATIC"}
                    }
    ],
    "generators":[
        {
            "generator": "plain",
            "min": 4,
            "max": 6
        }
    ],
    "derivative": "SWAMP"
}